utils/__init__.py
web_scraper_tool-0.1.0.dist-info/LICENSE
web_scraper_tool-0.1.0.dist-info/METADATA
web_scraper_tool-0.1.0.dist-info/WHEEL
web_scraper_tool-0.1.0.dist-info/entry_points.txt
web_scraper_tool-0.1.0.dist-info/top_level.txt
web_scraper_tool-0.1.0.dist-info/RECORD
